ticketml/__init__.py
ticketml/example_print.py
ticketml/ticketml.py
ticketml-0.2.3.dist-info/DESCRIPTION.rst
ticketml-0.2.3.dist-info/METADATA
ticketml-0.2.3.dist-info/RECORD
ticketml-0.2.3.dist-info/WHEEL
ticketml-0.2.3.dist-info/entry_points.txt
ticketml-0.2.3.dist-info/metadata.json
ticketml-0.2.3.dist-info/top_level.txt
