Metadata-Version: 2.0
Name: ticketml
Version: 0.2.3
Summary: TicketML is a simple markup language for receipt printers
Home-page: https://github.com/lukegb/ticketml
Author: Luke Granger-Brown
Author-email: git@lukegb.com
License: BSD
Keywords: ticketml
Platform: UNKNOWN
Classifier: Development Status :: 2 - Pre-Alpha
Classifier: Intended Audience :: Developers
Classifier: License :: OSI Approved :: BSD License
Classifier: Natural Language :: English
Classifier: Programming Language :: Python :: 2
Classifier: Programming Language :: Python :: 2.7
Classifier: Programming Language :: Python :: 3
Classifier: Programming Language :: Python :: 3.3
Classifier: Programming Language :: Python :: 3.4
Requires-Dist: enum34 (>=1.0.4)
Requires-Dist: lxml (>=3.4)
Requires-Dist: pySerial (>=2.7)
